[
  {
    "adr": "",
    "assujetti": true,
    "automatique": false,
    "base0Tva00": 0.000,
    "base1Tva06": 0.000,
    "base1Tva10": 0.000,
    "base1Tva18": 17.654,
    "base1Tva29": 0.000,
    "base2Tva06": 0.000,
    "base2Tva10": 0.000,
    "base2Tva18": 0.000,
    "base2Tva29": 0.000,
    "codAnes": "",
    "codAnnul": "",
    "codMed": "N001",
    "codPan": "",
    "codPans": "",
    "codcli": "418",
    "coddep": "99",
    "codeLivraisonBloc": "",
    "codfrs": "",
    "codrem": "0",
    "codrep": "",
    "codtva": "",
    "codvend": "SABRINE BT",
    "contr": "",
    "datAnnul": {
      "orig_eon": null,
      "orig_year": 1900,
      "orig_month": 1,
      "orig_day": 1,
      "orig_hour": 0,
      "orig_minute": 0,
      "orig_second": 0,
      "orig_fracSeconds": null,
      "orig_timezone": 60,
      "eon": null,
      "year": 1900,
      "month": 1,
      "day": 1,
      "timezone": 60,
      "hour": 0,
      "minute": 0,
      "second": 0,
      "fractionalSecond": null
    },
    "datRefFrs": {
      "orig_eon": null,
      "orig_year": 1900,
      "orig_month": 1,
      "orig_day": 1,
      "orig_hour": 0,
      "orig_minute": 0,
      "orig_second": 0,
      "orig_fracSeconds": null,
      "orig_timezone": 60,
      "eon": null,
      "year": 1900,
      "month": 1,
      "day": 1,
      "timezone": 60,
      "hour": 0,
      "minute": 0,
      "second": 0,
      "fractionalSecond": null
    },
    "datbon": {
      "orig_eon": null,
      "orig_year": 2017,
      "orig_month": 3,
      "orig_day": 11,
      "orig_hour": 0,
      "orig_minute": 0,
      "orig_second": 0,
      "orig_fracSeconds": null,
      "orig_timezone": 60,
      "eon": null,
      "year": 2017,
      "month": 3,
      "day": 11,
      "timezone": 60,
      "hour": 0,
      "minute": 0,
      "second": 0,
      "fractionalSecond": null
    },
    "datepiece": {
      "orig_eon": null,
      "orig_year": 1900,
      "orig_month": 1,
      "orig_day": 1,
      "orig_hour": 0,
      "orig_minute": 0,
      "orig_second": 0,
      "orig_fracSeconds": null,
      "orig_timezone": 60,
      "eon": null,
      "year": 1900,
      "month": 1,
      "day": 1,
      "timezone": 60,
      "hour": 0,
      "minute": 0,
      "second": 0,
      "fractionalSecond": null
    },
    "datesys": {
      "orig_eon": null,
      "orig_year": 2017,
      "orig_month": 3,
      "orig_day": 11,
      "orig_hour": 0,
      "orig_minute": 0,
      "orig_second": 0,
      "orig_fracSeconds": null,
      "orig_timezone": 60,
      "eon": null,
      "year": 2017,
      "month": 3,
      "day": 11,
      "timezone": 60,
      "hour": 0,
      "minute": 0,
      "second": 0,
      "fractionalSecond": null
    },
    "delai": 0,
    "depot": {
      "aControler": false,
      "codFrs": "",
      "coddep": "99",
      "correspondance": "",
      "depotFrs": false,
      "desdep": "Pharmacie Centrale",
      "orthopedie": false,
      "ouvrenouvex": false,
      "service": false,
      "stup": false,
      "valoriser": false,
      "vldCge1": 48,
      "vldCge2": 48
    },
    "deptr": "",
    "desdepa": "",
    "desdepd": "",
    "diagnost": null,
    "emis": "",
    "etatbon": false,
    "examen": null,
    "fodcli": false,
    "frais": 0.000,
    "gest": "",
    "heuresys": {
      "orig_eon": null,
      "orig_year": 2017,
      "orig_month": 3,
      "orig_day": 11,
      "orig_hour": 15,
      "orig_minute": 32,
      "orig_second": 34,
      "orig_fracSeconds": 0.063,
      "orig_timezone": 60,
      "eon": null,
      "year": 2017,
      "month": 3,
      "day": 11,
      "timezone": 60,
      "hour": 15,
      "minute": 32,
      "second": 34,
      "fractionalSecond": 0.063
    },
    "imprimer": false,
    "interdepot": false,
    "listdetails": [
      {
        "ancienQte": 0.000,
        "ancienValfod": 0.000,
        "ancienValrem": 0.000,
        "article": {
          "actif": true,
          "codart": "G008",
          "desart": "GANT D EXAMEN MEDIUM / PAQ",
          "facturable": false,
          "famille": {
            "codFamMere": "PTC",
            "cptFacNP": "602002",
            "cptStock": "372002",
            "cptVariationStock": "603202",
            "desFam": "PRODUITS CONSOMMABLES",
            "famArt": "PTC",
            "mntRealN": 0.000,
            "numcpt": "602002",
            "posologie": null,
            "unite": ""
          },
          "fodec": false,
          "forcerF2": false,
          "homologue": false,
          "marge": 100.000,
          "memoArt": "",
          "nbrPce": 1,
          "priach": 6.50000,
          "prittc": 0.00000,
          "priuni": 17.65400,
          "pvp": 0.00000,
          "qtestk": 716.000,
          "tauRem": 0.000,
          "tvavnt": "3"
        },
        "codtva": "3",
        "codvend": "",
        "datArr": {
          "orig_eon": null,
          "orig_year": 1900,
          "orig_month": 1,
          "orig_day": 1,
          "orig_hour": 0,
          "orig_minute": 0,
          "orig_second": 0,
          "orig_fracSeconds": null,
          "orig_timezone": 60,
          "eon": null,
          "year": 1900,
          "month": 1,
          "day": 1,
          "timezone": 60,
          "hour": 0,
          "minute": 0,
          "second": 0,
          "fractionalSecond": null
        },
        "datPer": null,
        "datbon": {
          "orig_eon": null,
          "orig_year": 2017,
          "orig_month": 3,
          "orig_day": 11,
          "orig_hour": 0,
          "orig_minute": 0,
          "orig_second": 0,
          "orig_fracSeconds": null,
          "orig_timezone": 60,
          "eon": null,
          "year": 2017,
          "month": 3,
          "day": 11,
          "timezone": 60,
          "hour": 0,
          "minute": 0,
          "second": 0,
          "fractionalSecond": null
        },
        "datefacbl": {
          "orig_eon": null,
          "orig_year": 1900,
          "orig_month": 1,
          "orig_day": 1,
          "orig_hour": 0,
          "orig_minute": 0,
          "orig_second": 0,
          "orig_fracSeconds": null,
          "orig_timezone": 60,
          "eon": null,
          "year": 1900,
          "month": 1,
          "day": 1,
          "timezone": 60,
          "hour": 0,
          "minute": 0,
          "second": 0,
          "fractionalSecond": null
        },
        "datinv": {
          "orig_eon": null,
          "orig_year": 1900,
          "orig_month": 1,
          "orig_day": 1,
          "orig_hour": 0,
          "orig_minute": 0,
          "orig_second": 0,
          "orig_fracSeconds": null,
          "orig_timezone": 60,
          "eon": null,
          "year": 1900,
          "month": 1,
          "day": 1,
          "timezone": 60,
          "hour": 0,
          "minute": 0,
          "second": 0,
          "fractionalSecond": null
        },
        "datinvDep": {
          "orig_eon": null,
          "orig_year": 1900,
          "orig_month": 1,
          "orig_day": 1,
          "orig_hour": 0,
          "orig_minute": 0,
          "orig_second": 0,
          "orig_fracSeconds": null,
          "orig_timezone": 60,
          "eon": null,
          "year": 1900,
          "month": 1,
          "day": 1,
          "timezone": 60,
          "hour": 0,
          "minute": 0,
          "second": 0,
          "fractionalSecond": null
        },
        "deptr": "",
        "desart": "GANT D EXAMEN MEDIUM / PAQ",
        "etat": "0",
        "etatDep": "0",
        "fodart": false,
        "gest": "",
        "heureSysteme": {
          "orig_eon": null,
          "orig_year": 2017,
          "orig_month": 3,
          "orig_day": 11,
          "orig_hour": 15,
          "orig_minute": 32,
          "orig_second": 34,
          "orig_fracSeconds": 0.063,
          "orig_timezone": 60,
          "eon": null,
          "year": 2017,
          "month": 3,
          "day": 11,
          "timezone": 60,
          "hour": 15,
          "minute": 32,
          "second": 34,
          "fractionalSecond": 0.063
        },
        "homologue": false,
        "majoration": 0.000,
        "marge": 100.000,
        "medtrait": "N001",
        "memoart": "",
        "modifier": "0",
        "montht": 17.654,
        "mvtstoPK": {
          "codart": "G008",
          "coddep": "99",
          "lot": "170211DADA102374",
          "numbon": "DADA102374",
          "numordre": "DA001"
        },
        "nbrpce": 1,
        "numBonDepot": "",
        "numCha": "152",
        "numVir": "",
        "numaffiche": "DA102374",
        "numdoss": "17002139",
        "numfacbl": "",
        "poids": null,
        "priAchApresProrata": 0.000,
        "priach": 6.407,
        "priuni": 17.65400,
        "prixben": 17.654,
        "pvp": 0.000,
        "qteAnest": null,
        "qteArr": 0.000,
        "qtePans": null,
        "qteben": 1.000,
        "qtecom": 1.000,
        "quantite": 1.000,
        "reference": "",
        "remise": 0.00000,
        "satisfait": "",
        "solde": 0.000,
        "tautva": 18.000,
        "typbon": "DA",
        "typmvt": "S",
        "utilis": "SABRINE BT"
      }
    ],
    "maintenance": "",
    "majoration": 0.000,
    "medecin": "MANAI RACHID",
    "memop": "",
    "mntFrs": 0.000,
    "mntRemise2": 0.000,
    "mntbon": 335.426,
    "modreg": "",
    "mp": "",
    "natadm": "Interne",
    "nature": "",
    "nuit": false,
    "numCha": "152",
    "numVir": "",
    "numaffiche": "DA102374",
    "numbon": "DADA102374",
    "numdoss": "17002139",
    "numfacbl": "",
    "numfacblaff": "",
    "numpiece": "",
    "ordon": "",
    "paniercb": null,
    "prorata": 0.000,
    "quittance": false,
    "raisoc": "SAAD  KHEMICI ",
    "rea": false,
    "reffrs": "",
    "remise": 0.000,
    "satisf": "NST",
    "satisfait": "",
    "smfodec": 0.000,
    "taufodec": 0.000,
    "tauxRemise2": 0.00000,
    "timbre": false,
    "tva10": 0.000,
    "tva18": 317.772,
    "tva29": 0.000,
    "tva6": 0.000,
    "txMajoration": 0.000,
    "typCB": "",
    "typbon": "DA",
    "typexon": 1,
    "valrem": 0.000,
    "valtimbre": 0.000
  },
  {
    "adr": "",
    "assujetti": true,
    "automatique": false,
    "base0Tva00": 0.000,
    "base1Tva06": 1.861,
    "base1Tva10": 0.000,
    "base1Tva18": 0.000,
    "base1Tva29": 0.000,
    "base2Tva06": 0.000,
    "base2Tva10": 0.000,
    "base2Tva18": 0.000,
    "base2Tva29": 0.000,
    "codAnes": "",
    "codAnnul": "",
    "codMed": "N001",
    "codPan": "",
    "codPans": "",
    "codcli": "418",
    "coddep": "99",
    "codeLivraisonBloc": "",
    "codfrs": "",
    "codrem": "0",
    "codrep": "",
    "codtva": "",
    "codvend": "REFKA BT N",
    "contr": "",
    "datAnnul": {
      "orig_eon": null,
      "orig_year": 1900,
      "orig_month": 1,
      "orig_day": 1,
      "orig_hour": 0,
      "orig_minute": 0,
      "orig_second": 0,
      "orig_fracSeconds": null,
      "orig_timezone": 60,
      "eon": null,
      "year": 1900,
      "month": 1,
      "day": 1,
      "timezone": 60,
      "hour": 0,
      "minute": 0,
      "second": 0,
      "fractionalSecond": null
    },
    "datRefFrs": {
      "orig_eon": null,
      "orig_year": 1900,
      "orig_month": 1,
      "orig_day": 1,
      "orig_hour": 0,
      "orig_minute": 0,
      "orig_second": 0,
      "orig_fracSeconds": null,
      "orig_timezone": 60,
      "eon": null,
      "year": 1900,
      "month": 1,
      "day": 1,
      "timezone": 60,
      "hour": 0,
      "minute": 0,
      "second": 0,
      "fractionalSecond": null
    },
    "datbon": {
      "orig_eon": null,
      "orig_year": 2017,
      "orig_month": 3,
      "orig_day": 16,
      "orig_hour": 0,
      "orig_minute": 0,
      "orig_second": 0,
      "orig_fracSeconds": null,
      "orig_timezone": 60,
      "eon": null,
      "year": 2017,
      "month": 3,
      "day": 16,
      "timezone": 60,
      "hour": 0,
      "minute": 0,
      "second": 0,
      "fractionalSecond": null
    },
    "datepiece": {
      "orig_eon": null,
      "orig_year": 1900,
      "orig_month": 1,
      "orig_day": 1,
      "orig_hour": 0,
      "orig_minute": 0,
      "orig_second": 0,
      "orig_fracSeconds": null,
      "orig_timezone": 60,
      "eon": null,
      "year": 1900,
      "month": 1,
      "day": 1,
      "timezone": 60,
      "hour": 0,
      "minute": 0,
      "second": 0,
      "fractionalSecond": null
    },
    "datesys": {
      "orig_eon": null,
      "orig_year": 2017,
      "orig_month": 3,
      "orig_day": 16,
      "orig_hour": 0,
      "orig_minute": 0,
      "orig_second": 0,
      "orig_fracSeconds": null,
      "orig_timezone": 60,
      "eon": null,
      "year": 2017,
      "month": 3,
      "day": 16,
      "timezone": 60,
      "hour": 0,
      "minute": 0,
      "second": 0,
      "fractionalSecond": null
    },
    "delai": 0,
    "depot": {
      "aControler": false,
      "codFrs": "",
      "coddep": "99",
      "correspondance": "",
      "depotFrs": false,
      "desdep": "Pharmacie Centrale",
      "orthopedie": false,
      "ouvrenouvex": false,
      "service": false,
      "stup": false,
      "valoriser": false,
      "vldCge1": 48,
      "vldCge2": 48
    },
    "deptr": "",
    "desdepa": "",
    "desdepd": "",
    "diagnost": null,
    "emis": "",
    "etatbon": false,
    "examen": null,
    "fodcli": false,
    "frais": 0.000,
    "gest": "",
    "heuresys": {
      "orig_eon": null,
      "orig_year": 2017,
      "orig_month": 3,
      "orig_day": 16,
      "orig_hour": 14,
      "orig_minute": 58,
      "orig_second": 39,
      "orig_fracSeconds": 0.570,
      "orig_timezone": 60,
      "eon": null,
      "year": 2017,
      "month": 3,
      "day": 16,
      "timezone": 60,
      "hour": 14,
      "minute": 58,
      "second": 39,
      "fractionalSecond": 0.570
    },
    "imprimer": false,
    "interdepot": false,
    "listdetails": [
      {
        "ancienQte": 0.000,
        "ancienValfod": 0.000,
        "ancienValrem": 0.000,
        "article": {
          "actif": true,
          "codart": "B080",
          "desart": "BANDE GAZE 10CM",
          "facturable": false,
          "famille": {
            "codFamMere": "PTC",
            "cptFacNP": "602002",
            "cptStock": "372002",
            "cptVariationStock": "603202",
            "desFam": "PRODUITS CONSOMMABLES",
            "famArt": "PTC",
            "mntRealN": 0.000,
            "numcpt": "602002",
            "posologie": null,
            "unite": ""
          },
          "fodec": true,
          "forcerF2": false,
          "homologue": false,
          "marge": 109.000,
          "memoArt": "",
          "nbrPce": 1,
          "priach": 0.44300,
          "prittc": 0.00000,
          "priuni": 0.93005,
          "pvp": 0.00000,
          "qtestk": 154.000,
          "tauRem": 0.000,
          "tvavnt": "1"
        },
        "codtva": "1",
        "codvend": "",
        "datArr": {
          "orig_eon": null,
          "orig_year": 1900,
          "orig_month": 1,
          "orig_day": 1,
          "orig_hour": 0,
          "orig_minute": 0,
          "orig_second": 0,
          "orig_fracSeconds": null,
          "orig_timezone": 60,
          "eon": null,
          "year": 1900,
          "month": 1,
          "day": 1,
          "timezone": 60,
          "hour": 0,
          "minute": 0,
          "second": 0,
          "fractionalSecond": null
        },
        "datPer": null,
        "datbon": {
          "orig_eon": null,
          "orig_year": 2017,
          "orig_month": 3,
          "orig_day": 16,
          "orig_hour": 0,
          "orig_minute": 0,
          "orig_second": 0,
          "orig_fracSeconds": null,
          "orig_timezone": 60,
          "eon": null,
          "year": 2017,
          "month": 3,
          "day": 16,
          "timezone": 60,
          "hour": 0,
          "minute": 0,
          "second": 0,
          "fractionalSecond": null
        },
        "datefacbl": {
          "orig_eon": null,
          "orig_year": 1900,
          "orig_month": 1,
          "orig_day": 1,
          "orig_hour": 0,
          "orig_minute": 0,
          "orig_second": 0,
          "orig_fracSeconds": null,
          "orig_timezone": 60,
          "eon": null,
          "year": 1900,
          "month": 1,
          "day": 1,
          "timezone": 60,
          "hour": 0,
          "minute": 0,
          "second": 0,
          "fractionalSecond": null
        },
        "datinv": {
          "orig_eon": null,
          "orig_year": 1900,
          "orig_month": 1,
          "orig_day": 1,
          "orig_hour": 0,
          "orig_minute": 0,
          "orig_second": 0,
          "orig_fracSeconds": null,
          "orig_timezone": 60,
          "eon": null,
          "year": 1900,
          "month": 1,
          "day": 1,
          "timezone": 60,
          "hour": 0,
          "minute": 0,
          "second": 0,
          "fractionalSecond": null
        },
        "datinvDep": {
          "orig_eon": null,
          "orig_year": 1900,
          "orig_month": 1,
          "orig_day": 1,
          "orig_hour": 0,
          "orig_minute": 0,
          "orig_second": 0,
          "orig_fracSeconds": null,
          "orig_timezone": 60,
          "eon": null,
          "year": 1900,
          "month": 1,
          "day": 1,
          "timezone": 60,
          "hour": 0,
          "minute": 0,
          "second": 0,
          "fractionalSecond": null
        },
        "deptr": "",
        "desart": "BANDE GAZE 10CM",
        "etat": "0",
        "etatDep": "0",
        "fodart": true,
        "gest": "",
        "heureSysteme": {
          "orig_eon": null,
          "orig_year": 2017,
          "orig_month": 3,
          "orig_day": 16,
          "orig_hour": 14,
          "orig_minute": 58,
          "orig_second": 39,
          "orig_fracSeconds": 0.570,
          "orig_timezone": 60,
          "eon": null,
          "year": 2017,
          "month": 3,
          "day": 16,
          "timezone": 60,
          "hour": 14,
          "minute": 58,
          "second": 39,
          "fractionalSecond": 0.570
        },
        "homologue": false,
        "majoration": 0.000,
        "marge": 109.000,
        "medtrait": "N001",
        "memoart": "",
        "modifier": "0",
        "montht": 1.861,
        "mvtstoPK": {
          "codart": "B080",
          "coddep": "99",
          "lot": "170216DADA102405",
          "numbon": "DADA102405",
          "numordre": "DA001"
        },
        "nbrpce": 1,
        "numBonDepot": "",
        "numCha": "158",
        "numVir": "",
        "numaffiche": "DA102405",
        "numdoss": "16021064",
        "numfacbl": "",
        "poids": null,
        "priAchApresProrata": 0.000,
        "priach": 0.445,
        "priuni": 0.93005,
        "prixben": 0.930,
        "pvp": 0.000,
        "qteAnest": null,
        "qteArr": 0.000,
        "qtePans": null,
        "qteben": 2.000,
        "qtecom": 2.000,
        "quantite": 2.000,
        "reference": "",
        "remise": 0.00000,
        "satisfait": "",
        "solde": 0.000,
        "tautva": 6.000,
        "typbon": "DA",
        "typmvt": "S",
        "utilis": "REFKA BT N"
      }
    ],
    "maintenance": "",
    "majoration": 0.000,
    "medecin": "MANAI RACHID",
    "memop": "",
    "mntFrs": 0.000,
    "mntRemise2": 0.000,
    "mntbon": 13.027,
    "modreg": "",
    "mp": "",
    "natadm": "Interne",
    "nature": "",
    "nuit": false,
    "numCha": "158",
    "numVir": "",
    "numaffiche": "DA102405",
    "numbon": "DADA102405",
    "numdoss": "16021064",
    "numfacbl": "",
    "numfacblaff": "",
    "numpiece": "",
    "ordon": "",
    "paniercb": null,
    "prorata": 0.000,
    "quittance": false,
    "raisoc": "ZRIG ACHREF ",
    "rea": false,
    "reffrs": "",
    "remise": 0.000,
    "satisf": "NST",
    "satisfait": "",
    "smfodec": 0.000,
    "taufodec": 0.000,
    "tauxRemise2": 0.00000,
    "timbre": false,
    "tva10": 0.000,
    "tva18": 0.000,
    "tva29": 0.000,
    "tva6": 11.166,
    "txMajoration": 0.000,
    "typCB": "",
    "typbon": "DA",
    "typexon": 1,
    "valrem": 0.000,
    "valtimbre": 0.000
  },
  {
    "adr": "",
    "assujetti": true,
    "automatique": false,
    "base0Tva00": 0.000,
    "base1Tva06": 6.823,
    "base1Tva10": 0.000,
    "base1Tva18": 0.000,
    "base1Tva29": 0.000,
    "base2Tva06": 0.000,
    "base2Tva10": 0.000,
    "base2Tva18": 0.000,
    "base2Tva29": 0.000,
    "codAnes": "",
    "codAnnul": "",
    "codMed": "N001",
    "codPan": "",
    "codPans": "",
    "codcli": "418",
    "coddep": "99",
    "codeLivraisonBloc": "",
    "codfrs": "",
    "codrem": "0",
    "codrep": "",
    "codtva": "",
    "codvend": "REFKA BT N",
    "contr": "",
    "datAnnul": {
      "orig_eon": null,
      "orig_year": 1900,
      "orig_month": 1,
      "orig_day": 1,
      "orig_hour": 0,
      "orig_minute": 0,
      "orig_second": 0,
      "orig_fracSeconds": null,
      "orig_timezone": 60,
      "eon": null,
      "year": 1900,
      "month": 1,
      "day": 1,
      "timezone": 60,
      "hour": 0,
      "minute": 0,
      "second": 0,
      "fractionalSecond": null
    },
    "datRefFrs": {
      "orig_eon": null,
      "orig_year": 1900,
      "orig_month": 1,
      "orig_day": 1,
      "orig_hour": 0,
      "orig_minute": 0,
      "orig_second": 0,
      "orig_fracSeconds": null,
      "orig_timezone": 60,
      "eon": null,
      "year": 1900,
      "month": 1,
      "day": 1,
      "timezone": 60,
      "hour": 0,
      "minute": 0,
      "second": 0,
      "fractionalSecond": null
    },
    "datbon": {
      "orig_eon": null,
      "orig_year": 2017,
      "orig_month": 3,
      "orig_day": 16,
      "orig_hour": 0,
      "orig_minute": 0,
      "orig_second": 0,
      "orig_fracSeconds": null,
      "orig_timezone": 60,
      "eon": null,
      "year": 2017,
      "month": 3,
      "day": 16,
      "timezone": 60,
      "hour": 0,
      "minute": 0,
      "second": 0,
      "fractionalSecond": null
    },
    "datepiece": {
      "orig_eon": null,
      "orig_year": 1900,
      "orig_month": 1,
      "orig_day": 1,
      "orig_hour": 0,
      "orig_minute": 0,
      "orig_second": 0,
      "orig_fracSeconds": null,
      "orig_timezone": 60,
      "eon": null,
      "year": 1900,
      "month": 1,
      "day": 1,
      "timezone": 60,
      "hour": 0,
      "minute": 0,
      "second": 0,
      "fractionalSecond": null
    },
    "datesys": {
      "orig_eon": null,
      "orig_year": 2017,
      "orig_month": 3,
      "orig_day": 16,
      "orig_hour": 0,
      "orig_minute": 0,
      "orig_second": 0,
      "orig_fracSeconds": null,
      "orig_timezone": 60,
      "eon": null,
      "year": 2017,
      "month": 3,
      "day": 16,
      "timezone": 60,
      "hour": 0,
      "minute": 0,
      "second": 0,
      "fractionalSecond": null
    },
    "delai": 0,
    "depot": {
      "aControler": false,
      "codFrs": "",
      "coddep": "99",
      "correspondance": "",
      "depotFrs": false,
      "desdep": "Pharmacie Centrale",
      "orthopedie": false,
      "ouvrenouvex": false,
      "service": false,
      "stup": false,
      "valoriser": false,
      "vldCge1": 48,
      "vldCge2": 48
    },
    "deptr": "",
    "desdepa": "",
    "desdepd": "",
    "diagnost": null,
    "emis": "",
    "etatbon": false,
    "examen": null,
    "fodcli": false,
    "frais": 0.000,
    "gest": "",
    "heuresys": {
      "orig_eon": null,
      "orig_year": 2017,
      "orig_month": 3,
      "orig_day": 16,
      "orig_hour": 14,
      "orig_minute": 59,
      "orig_second": 43,
      "orig_fracSeconds": 0.983,
      "orig_timezone": 60,
      "eon": null,
      "year": 2017,
      "month": 3,
      "day": 16,
      "timezone": 60,
      "hour": 14,
      "minute": 59,
      "second": 43,
      "fractionalSecond": 0.983
    },
    "imprimer": false,
    "interdepot": false,
    "listdetails": [
      {
        "ancienQte": 0.000,
        "ancienValfod": 0.000,
        "ancienValrem": 0.000,
        "article": {
          "actif": true,
          "codart": "B093",
          "desart": "BANDE BIPLATRIX DE 10",
          "facturable": false,
          "famille": {
            "codFamMere": "PTC",
            "cptFacNP": "602002",
            "cptStock": "372002",
            "cptVariationStock": "603202",
            "desFam": "PRODUITS CONSOMMABLES",
            "famArt": "PTC",
            "mntRealN": 0.000,
            "numcpt": "602002",
            "posologie": null,
            "unite": ""
          },
          "fodec": false,
          "forcerF2": false,
          "homologue": false,
          "marge": 54.500,
          "memoArt": "",
          "nbrPce": 1,
          "priach": 2.20000,
          "prittc": 0.00000,
          "priuni": 3.41136,
          "pvp": 0.00000,
          "qtestk": 264.000,
          "tauRem": 0.000,
          "tvavnt": "1"
        },
        "codtva": "1",
        "codvend": "",
        "datArr": {
          "orig_eon": null,
          "orig_year": 1900,
          "orig_month": 1,
          "orig_day": 1,
          "orig_hour": 0,
          "orig_minute": 0,
          "orig_second": 0,
          "orig_fracSeconds": null,
          "orig_timezone": 60,
          "eon": null,
          "year": 1900,
          "month": 1,
          "day": 1,
          "timezone": 60,
          "hour": 0,
          "minute": 0,
          "second": 0,
          "fractionalSecond": null
        },
        "datPer": null,
        "datbon": {
          "orig_eon": null,
          "orig_year": 2017,
          "orig_month": 3,
          "orig_day": 16,
          "orig_hour": 0,
          "orig_minute": 0,
          "orig_second": 0,
          "orig_fracSeconds": null,
          "orig_timezone": 60,
          "eon": null,
          "year": 2017,
          "month": 3,
          "day": 16,
          "timezone": 60,
          "hour": 0,
          "minute": 0,
          "second": 0,
          "fractionalSecond": null
        },
        "datefacbl": {
          "orig_eon": null,
          "orig_year": 1900,
          "orig_month": 1,
          "orig_day": 1,
          "orig_hour": 0,
          "orig_minute": 0,
          "orig_second": 0,
          "orig_fracSeconds": null,
          "orig_timezone": 60,
          "eon": null,
          "year": 1900,
          "month": 1,
          "day": 1,
          "timezone": 60,
          "hour": 0,
          "minute": 0,
          "second": 0,
          "fractionalSecond": null
        },
        "datinv": {
          "orig_eon": null,
          "orig_year": 1900,
          "orig_month": 1,
          "orig_day": 1,
          "orig_hour": 0,
          "orig_minute": 0,
          "orig_second": 0,
          "orig_fracSeconds": null,
          "orig_timezone": 60,
          "eon": null,
          "year": 1900,
          "month": 1,
          "day": 1,
          "timezone": 60,
          "hour": 0,
          "minute": 0,
          "second": 0,
          "fractionalSecond": null
        },
        "datinvDep": {
          "orig_eon": null,
          "orig_year": 1900,
          "orig_month": 1,
          "orig_day": 1,
          "orig_hour": 0,
          "orig_minute": 0,
          "orig_second": 0,
          "orig_fracSeconds": null,
          "orig_timezone": 60,
          "eon": null,
          "year": 1900,
          "month": 1,
          "day": 1,
          "timezone": 60,
          "hour": 0,
          "minute": 0,
          "second": 0,
          "fractionalSecond": null
        },
        "deptr": "",
        "desart": "BANDE BIPLATRIX DE 10",
        "etat": "0",
        "etatDep": "0",
        "fodart": false,
        "gest": "",
        "heureSysteme": {
          "orig_eon": null,
          "orig_year": 2017,
          "orig_month": 3,
          "orig_day": 16,
          "orig_hour": 14,
          "orig_minute": 59,
          "orig_second": 43,
          "orig_fracSeconds": 0.983,
          "orig_timezone": 60,
          "eon": null,
          "year": 2017,
          "month": 3,
          "day": 16,
          "timezone": 60,
          "hour": 14,
          "minute": 59,
          "second": 43,
          "fractionalSecond": 0.983
        },
        "homologue": false,
        "majoration": 0.000,
        "marge": 54.500,
        "medtrait": "N001",
        "memoart": "",
        "modifier": "0",
        "montht": 6.823,
        "mvtstoPK": {
          "codart": "B093",
          "coddep": "99",
          "lot": "170216DADA102406",
          "numbon": "DADA102406",
          "numordre": "DA001"
        },
        "nbrpce": 1,
        "numBonDepot": "",
        "numCha": "158",
        "numVir": "",
        "numaffiche": "DA102406",
        "numdoss": "16021064",
        "numfacbl": "",
        "poids": null,
        "priAchApresProrata": 0.000,
        "priach": 2.208,
        "priuni": 3.41136,
        "prixben": 3.411,
        "pvp": 0.000,
        "qteAnest": null,
        "qteArr": 0.000,
        "qtePans": null,
        "qteben": 2.000,
        "qtecom": 2.000,
        "quantite": 2.000,
        "reference": "",
        "remise": 0.00000,
        "satisfait": "",
        "solde": 0.000,
        "tautva": 6.000,
        "typbon": "DA",
        "typmvt": "S",
        "utilis": "REFKA BT N"
      }
    ],
    "maintenance": "",
    "majoration": 0.000,
    "medecin": "MANAI RACHID",
    "memop": "",
    "mntFrs": 0.000,
    "mntRemise2": 0.000,
    "mntbon": 47.761,
    "modreg": "",
    "mp": "",
    "natadm": "Interne",
    "nature": "",
    "nuit": false,
    "numCha": "158",
    "numVir": "",
    "numaffiche": "DA102406",
    "numbon": "DADA102406",
    "numdoss": "16021064",
    "numfacbl": "",
    "numfacblaff": "",
    "numpiece": "",
    "ordon": "",
    "paniercb": null,
    "prorata": 0.000,
    "quittance": false,
    "raisoc": "ZRIG ACHREF ",
    "rea": false,
    "reffrs": "",
    "remise": 0.000,
    "satisf": "NST",
    "satisfait": "",
    "smfodec": 0.000,
    "taufodec": 0.000,
    "tauxRemise2": 0.00000,
    "timbre": false,
    "tva10": 0.000,
    "tva18": 0.000,
    "tva29": 0.000,
    "tva6": 40.938,
    "txMajoration": 0.000,
    "typCB": "",
    "typbon": "DA",
    "typexon": 1,
    "valrem": 0.000,
    "valtimbre": 0.000
  }
]